pysolate.py
pysolate-0.1.0.data/scripts/pysolate
pysolate-0.1.0.dist-info/METADATA
pysolate-0.1.0.dist-info/WHEEL
pysolate-0.1.0.dist-info/top_level.txt
pysolate-0.1.0.dist-info/RECORD
